ontquery/__init__.py
ontquery/exceptions.py
ontquery/plugin.py
ontquery/query.py
ontquery/services.py
ontquery/terms.py
ontquery/trie.py
ontquery/utils.py
ontquery/plugins/__init__.py
ontquery/plugins/services/__init__.py
ontquery/plugins/services/auth-config.py
ontquery/plugins/services/interlex.py
ontquery/plugins/services/interlex_client.py
ontquery/plugins/services/interlex_session.py
ontquery/plugins/services/rdflib.py
ontquery/plugins/services/scigraph.py
ontquery/plugins/services/scigraph_client.py
ontquery-0.2.12.dist-info/licenses/LICENSE
ontquery-0.2.12.dist-info/METADATA
ontquery-0.2.12.dist-info/WHEEL
ontquery-0.2.12.dist-info/top_level.txt
ontquery-0.2.12.dist-info/RECORD
