Metadata-Version: 2.4
Name: ontquery
Version: 0.2.12
Summary: a framework querying ontology terms
Home-page: https://github.com/tgbugs/ontquery
Author: Tom Gillespie
Author-email: tgbugs@gmail.com
License: MIT
Keywords: ontology terminology scigraph interlex term lookup ols
Classifier: Development Status :: 4 - Beta
Classifier: License :: OSI Approved :: MIT License
Classifier: Programming Language :: Python :: 3.6
Classifier: Programming Language :: Python :: 3.7
Classifier: Programming Language :: Python :: 3.8
Classifier: Programming Language :: Python :: 3.9
Classifier: Programming Language :: Python :: 3.10
Classifier: Programming Language :: Python :: 3.11
Classifier: Programming Language :: Python :: Implementation :: CPython
Classifier: Programming Language :: Python :: Implementation :: PyPy
Classifier: Operating System :: POSIX :: Linux
Classifier: Operating System :: MacOS :: MacOS X
Classifier: Operating System :: Microsoft :: Windows
Requires-Python: >=3.6
License-File: LICENSE
Provides-Extra: dev
Requires-Dist: pyontutils>=0.1.5; extra == "dev"
Requires-Dist: pytest-cov; extra == "dev"
Requires-Dist: wheel; extra == "dev"
Provides-Extra: services
Requires-Dist: orthauth>=0.0.14; extra == "services"
Requires-Dist: pyontutils>=0.1.27; extra == "services"
Requires-Dist: rdflib>=6.0.0; extra == "services"
Requires-Dist: requests; extra == "services"
Provides-Extra: test
Requires-Dist: pytest; extra == "test"
Requires-Dist: orthauth>=0.0.14; extra == "test"
Requires-Dist: pyontutils>=0.1.27; extra == "test"
Requires-Dist: rdflib>=6.0.0; extra == "test"
Requires-Dist: requests; extra == "test"
Dynamic: author
Dynamic: author-email
Dynamic: classifier
Dynamic: description
Dynamic: description-content-type
Dynamic: home-page
Dynamic: keywords
Dynamic: license
Dynamic: license-file
Dynamic: provides-extra
Dynamic: requires-python
Dynamic: summary
